[{"message": "", "sentiment_response": {"type": "neutral", "score": 0, "ratio": 0, "keywords": [], "version": "7.5.7", "author": "twinword inc.", "email": "help@twinword.com", "result_code": "200", "result_msg": "Success"}}, {"message": "", "sentiment_response": {"type": "neutral", "score": 0, "ratio": 0, "keywords": [], "version": "7.5.7", "author": "twinword inc.", "email": "help@twinword.com", "result_code": "200", "result_msg": "Success"}}, {"message": "", "sentiment_response": {"type": "neutral", "score": 0, "ratio": 0, "keywords": [], "version": "7.5.7", "author": "twinword inc.", "email": "help@twinword.com", "result_code": "200", "result_msg": "Success"}}, {"message": "", "sentiment_response": {"type": "neutral", "score": 0, "ratio": 0, "keywords": [], "version": "7.5.7", "author": "twinword inc.", "email": "help@twinword.com", "result_code": "200", "result_msg": "Success"}}, {"message": "", "sentiment_response": {"type": "neutral", "score": 0, "ratio": 0, "keywords": [], "version": "7.5.7", "author": "twinword inc.", "email": "help@twinword.com", "result_code": "200", "result_msg": "Success"}}, {"message": "", "sentiment_response": {"type": "neutral", "score": 0, "ratio": 0, "keywords": [], "version": "7.5.7", "author": "twinword inc.", "email": "help@twinword.com", "result_code": "200", "result_msg": "Success"}}, {"message": "", "sentiment_response": {"type": "neutral", "score": 0, "ratio": 0, "keywords": [], "version": "7.5.7", "author": "twinword inc.", "email": "help@twinword.com", "result_code": "200", "result_msg": "Success"}}, {"message": "", "sentiment_response": {"type": "neutral", "score": 0, "ratio": 0, "keywords": [], "version": "7.5.7", "author": "twinword inc.", "email": "help@twinword.com", "result_code": "200", "result_msg": "Success"}}, {"message": "", "sentiment_response": {"type": "neutral", "score": 0, "ratio": 0, "keywords": [], "version": "7.5.7", "author": "twinword inc.", "email": "help@twinword.com", "result_code": "200", "result_msg": "Success"}}, {"message": "", "sentiment_response": {"type": "neutral", "score": 0, "ratio": 0, "keywords": [], "version": "7.5.7", "author": "twinword inc.", "email": "help@twinword.com", "result_code": "200", "result_msg": "Success"}}, {"message": "", "sentiment_response": {"type": "neutral", "score": 0, "ratio": 0, "keywords": [], "version": "7.5.7", "author": "twinword inc.", "email": "help@twinword.com", "result_code": "200", "result_msg": "Success"}}, {"message": "", "sentiment_response": {"type": "neutral", "score": 0, "ratio": 0, "keywords": [], "version": "7.5.7", "author": "twinword inc.", "email": "help@twinword.com", "result_code": "200", "result_msg": "Success"}}, {"message": "", "sentiment_response": {"type": "neutral", "score": 0, "ratio": 0, "keywords": [], "version": "7.5.7", "author": "twinword inc.", "email": "help@twinword.com", "result_code": "200", "result_msg": "Success"}}, {"message": "", "sentiment_response": {"type": "neutral", "score": 0, "ratio": 0, "keywords": [], "version": "7.5.7", "author": "twinword inc.", "email": "help@twinword.com", "result_code": "200", "result_msg": "Success"}}, {"message": "", "sentiment_response": {"type": "neutral", "score": 0, "ratio": 0, "keywords": [], "version": "7.5.7", "author": "twinword inc.", "email": "help@twinword.com", "result_code": "200", "result_msg": "Success"}}, {"message": "", "sentiment_response": {"type": "neutral", "score": 0, "ratio": 0, "keywords": [], "version": "7.5.7", "author": "twinword inc.", "email": "help@twinword.com", "result_code": "200", "result_msg": "Success"}}, {"message": "", "sentiment_response": {"type": "neutral", "score": 0, "ratio": 0, "keywords": [], "version": "7.5.7", "author": "twinword inc.", "email": "help@twinword.com", "result_code": "200", "result_msg": "Success"}}, {"message": "", "sentiment_response": {"type": "neutral", "score": 0, "ratio": 0, "keywords": [], "version": "7.5.7", "author": "twinword inc.", "email": "help@twinword.com", "result_code": "200", "result_msg": "Success"}}, {"message": "", "sentiment_response": {"type": "neutral", "score": 0, "ratio": 0, "keywords": [], "version": "7.5.7", "author": "twinword inc.", "email": "help@twinword.com", "result_code": "200", "result_msg": "Success"}}, {"message": "", "sentiment_response": {"type": "neutral", "score": 0, "ratio": 0, "keywords": [], "version": "7.5.7", "author": "twinword inc.", "email": "help@twinword.com", "result_code": "200", "result_msg": "Success"}}, {"message": "", "sentiment_response": {"type": "neutral", "score": 0, "ratio": 0, "keywords": [], "version": "7.5.7", "author": "twinword inc.", "email": "help@twinword.com", "result_code": "200", "result_msg": "Success"}}, {"message": "", "sentiment_response": {"type": "neutral", "score": 0, "ratio": 0, "keywords": [], "version": "7.5.7", "author": "twinword inc.", "email": "help@twinword.com", "result_code": "200", "result_msg": "Success"}}, {"message": "", "sentiment_response": {"type": "neutral", "score": 0, "ratio": 0, "keywords": [], "version": "7.5.7", "author": "twinword inc.", "email": "help@twinword.com", "result_code": "200", "result_msg": "Success"}}, {"message": "", "sentiment_response": {"type": "neutral", "score": 0, "ratio": 0, "keywords": [], "version": "7.5.7", "author": "twinword inc.", "email": "help@twinword.com", "result_code": "200", "result_msg": "Success"}}, {"message": "", "sentiment_response": {"type": "neutral", "score": 0, "ratio": 0, "keywords": [], "version": "7.5.7", "author": "twinword inc.", "email": "help@twinword.com", "result_code": "200", "result_msg": "Success"}}]